mastomsg.py
mastomsg-0.3.0.dist-info/LICENSE
mastomsg-0.3.0.dist-info/METADATA
mastomsg-0.3.0.dist-info/WHEEL
mastomsg-0.3.0.dist-info/entry_points.txt
mastomsg-0.3.0.dist-info/top_level.txt
mastomsg-0.3.0.dist-info/RECORD
