Metadata-Version: 2.2
Name: mastomsg
Version: 0.3.0
Summary: Tool to help mastodon server admins to conveniently reach certain parts of their user base with DMs.
Author-email: tante <tante@tante.cc>
Project-URL: Homepage, https://codeberg.org/tante/mastomsg
Project-URL: Repository, https://codeberg.org/tante/mastomsg
Project-URL: Issues, https://codeberg.org/tante/mastomsg/issues
Requires-Python: >=3.10
License-File: LICENSE
Requires-Dist: mastodon-py>=1.8.1
Requires-Dist: typer>=0.15.1
